fontTools/__init__.py
fontTools/__main__.py
fontTools/afmLib.py
fontTools/agl.py
fontTools/fontBuilder.py
fontTools/help.py
fontTools/tfmLib.py
fontTools/ttx.py
fontTools/unicode.py
fontTools/cffLib/CFF2ToCFF.py
fontTools/cffLib/CFFToCFF2.py
fontTools/cffLib/__init__.py
fontTools/cffLib/specializer.py
fontTools/cffLib/transforms.py
fontTools/cffLib/width.py
fontTools/colorLib/__init__.py
fontTools/colorLib/builder.py
fontTools/colorLib/errors.py
fontTools/colorLib/geometry.py
fontTools/colorLib/table_builder.py
fontTools/colorLib/unbuilder.py
fontTools/config/__init__.py
fontTools/cu2qu/__init__.py
fontTools/cu2qu/__main__.py
fontTools/cu2qu/benchmark.py
fontTools/cu2qu/cli.py
fontTools/cu2qu/cu2qu.py
fontTools/cu2qu/errors.py
fontTools/cu2qu/ufo.py
fontTools/designspaceLib/__init__.py
fontTools/designspaceLib/__main__.py
fontTools/designspaceLib/split.py
fontTools/designspaceLib/statNames.py
fontTools/designspaceLib/types.py
fontTools/encodings/MacRoman.py
fontTools/encodings/StandardEncoding.py
fontTools/encodings/__init__.py
fontTools/encodings/codecs.py
fontTools/feaLib/__init__.py
fontTools/feaLib/__main__.py
fontTools/feaLib/ast.py
fontTools/feaLib/builder.py
fontTools/feaLib/error.py
fontTools/feaLib/lexer.py
fontTools/feaLib/location.py
fontTools/feaLib/lookupDebugInfo.py
fontTools/feaLib/parser.py
fontTools/feaLib/variableScalar.py
fontTools/merge/__init__.py
fontTools/merge/__main__.py
fontTools/merge/base.py
fontTools/merge/cmap.py
fontTools/merge/layout.py
fontTools/merge/options.py
fontTools/merge/tables.py
fontTools/merge/unicode.py
fontTools/merge/util.py
fontTools/misc/__init__.py
fontTools/misc/arrayTools.py
fontTools/misc/bezierTools.py
fontTools/misc/classifyTools.py
fontTools/misc/cliTools.py
fontTools/misc/configTools.py
fontTools/misc/cython.py
fontTools/misc/dictTools.py
fontTools/misc/eexec.py
fontTools/misc/encodingTools.py
fontTools/misc/etree.py
fontTools/misc/filenames.py
fontTools/misc/fixedTools.py
fontTools/misc/intTools.py
fonttools-4.58.3.dist-info/licenses/LICENSE
fonttools-4.58.3.dist-info/licenses/LICENSE.external
fonttools-4.58.3.dist-info/METADATA
fonttools-4.58.3.dist-info/WHEEL
fonttools-4.58.3.dist-info/entry_points.txt
fonttools-4.58.3.dist-info/top_level.txt
fonttools-4.58.3.dist-info/RECORD
