Metadata-Version: 2.4
Name: fonttools
Version: 4.58.3
Summary: Tools to manipulate font files
Home-page: http://github.com/fonttools/fonttools
Author: Just van Rossum
Author-email: just@letterror.com
Maintainer: Behdad Esfahbod
Maintainer-email: behdad@behdad.org
License: MIT
Platform: Any
Classifier: Development Status :: 5 - Production/Stable
Classifier: Environment :: Console
Classifier: Environment :: Other Environment
Classifier: Intended Audience :: Developers
Classifier: Intended Audience :: End Users/Desktop
Classifier: Natural Language :: English
Classifier: Operating System :: OS Independent
Classifier: Programming Language :: Python
Classifier: Programming Language :: Python :: 3.9
Classifier: Programming Language :: Python :: 3.10
Classifier: Programming Language :: Python :: 3.11
Classifier: Programming Language :: Python :: 3.12
Classifier: Programming Language :: Python :: 3.13
Classifier: Programming Language :: Python :: 3
Classifier: Topic :: Text Processing :: Fonts
Classifier: Topic :: Multimedia :: Graphics
Classifier: Topic :: Multimedia :: Graphics :: Graphics Conversion
Requires-Python: >=3.9
License-File: LICENSE
License-File: LICENSE.external
Provides-Extra: ufo
Requires-Dist: fs<3,>=2.2.0; extra == "ufo"
Provides-Extra: lxml
Requires-Dist: lxml>=4.0; extra == "lxml"
Provides-Extra: woff
Requires-Dist: brotli>=1.0.1; platform_python_implementation == "CPython" and extra == "woff"
Requires-Dist: brotlicffi>=0.8.0; platform_python_implementation != "CPython" and extra == "woff"
Requires-Dist: zopfli>=0.1.4; extra == "woff"
Provides-Extra: unicode
Requires-Dist: unicodedata2>=15.1.0; python_version <= "3.12" and extra == "unicode"
Provides-Extra: graphite
Requires-Dist: lz4>=1.7.4.2; extra == "graphite"
Provides-Extra: interpolatable
Requires-Dist: scipy; platform_python_implementation != "PyPy" and extra == "interpolatable"
Requires-Dist: munkres; platform_python_implementation == "PyPy" and extra == "interpolatable"
Requires-Dist: pycairo; extra == "interpolatable"
Provides-Extra: plot
Requires-Dist: matplotlib; extra == "plot"
Provides-Extra: symfont
Requires-Dist: sympy; extra == "symfont"
Provides-Extra: type1
Requires-Dist: xattr; sys_platform == "darwin" and extra == "type1"
Provides-Extra: pathops
Requires-Dist: skia-pathops>=0.5.0; extra == "pathops"
Provides-Extra: repacker
Requires-Dist: uharfbuzz>=0.23.0; extra == "repacker"
Provides-Extra: all
Requires-Dist: fs<3,>=2.2.0; extra == "all"
Requires-Dist: lxml>=4.0; extra == "all"
Requires-Dist: brotli>=1.0.1; platform_python_implementation == "CPython" and extra == "all"
Requires-Dist: brotlicffi>=0.8.0; platform_python_implementation != "CPython" and extra == "all"
Requires-Dist: zopfli>=0.1.4; extra == "all"
Requires-Dist: unicodedata2>=15.1.0; python_version <= "3.12" and extra == "all"
Requires-Dist: lz4>=1.7.4.2; extra == "all"
Requires-Dist: scipy; platform_python_implementation != "PyPy" and extra == "all"
Requires-Dist: munkres; platform_python_implementation == "PyPy" and extra == "all"
Requires-Dist: pycairo; extra == "all"
Requires-Dist: matplotlib; extra == "all"
Requires-Dist: sympy; extra == "all"
Requires-Dist: xattr; sys_platform == "darwin" and extra == "all"
Requires-Dist: skia-pathops>=0.5.0; extra == "all"
Requires-Dist: uharfbuzz>=0.23.0; extra == "all"
Dynamic: author
Dynamic: author-email
Dynamic: classifier
Dynamic: description
Dynamic: description-content-type
Dynamic: home-page
Dynamic: license
Dynamic: license-file
Dynamic: maintainer
Dynamic: maintainer-email
Dynamic: platform
Dynamic: provides-extra
Dynamic: requires-python
Dynamic: summary
